lastlogcsv/__init__.py
lastlogcsv/__main__.py
lastlogcsv/parser.py
lastlogcsv/py.typed
lastlogcsv-2.0.0.dist-info/LICENSE
lastlogcsv-2.0.0.dist-info/METADATA
lastlogcsv-2.0.0.dist-info/WHEEL
lastlogcsv-2.0.0.dist-info/entry_points.txt
lastlogcsv-2.0.0.dist-info/top_level.txt
lastlogcsv-2.0.0.dist-info/zip-safe
lastlogcsv-2.0.0.dist-info/RECORD
