Metadata-Version: 2.1
Name: lastlogcsv
Version: 2.0.0
Summary: Converter from /var/log/lastlog to csv file.
Home-page: https://github.com/Dashstrom/lastlogcsv
Author: Dashstrom
Author-email: dashstrom.pro@gmail.com
License: GPL-3.0 License
Keywords: lastlog,parser,script,forensics,csv
Platform: any
Classifier: License :: OSI Approved :: GNU General Public License v3 (GPLv3)
Classifier: Programming Language :: Python :: 3
Classifier: Programming Language :: Python :: 3.6
Classifier: Programming Language :: Python :: 3.7
Classifier: Programming Language :: Python :: 3.8
Classifier: Programming Language :: Python :: 3.9
Classifier: Programming Language :: Python :: 3.10
Classifier: Operating System :: Microsoft :: Windows
Classifier: Operating System :: MacOS
Classifier: Operating System :: POSIX :: Linux
Requires-Python: >=3.6.0
License-File: LICENSE
Requires-Dist: future (>=0.18.2)
Requires-Dist: pip (>=18.1)
Requires-Dist: setuptools (>=40.6.2)
Requires-Dist: typing-extensions (>=4.1.1)
Requires-Dist: wheel (>=0.37.1)
